[
    {
        "品牌": "Estee Lauder 雅詩蘭黛",
        "產品編號": "8941303",
        "產品名": "【Estee Lauder 雅詩蘭黛】小棕新粉組(特潤超導全方位修護露30ml (小棕瓶/精華液))",
        "產品系列": "Home\\彩妝保養\\專櫃保養品牌\\官方直營品牌\\EsteeLauder",
        "優惠期間": "09/13~09/18",
        "產品描述": "['一滴完美透亮', '肌膚彈潤更緊緻', '極速修護新革命']",
        "所有價格": {
            "市售價": 3530,
            "促銷價": 2950,
            "折扣後價格": 2750
        },
        "資料更新時間": "2022-09-16 01:24:23"
    },
    {
        "品牌": "Estee Lauder 雅詩蘭黛",
        "產品編號": "9486768",
        "產品名": "【Estee Lauder 雅詩蘭黛】粉持久新客組(粉持久完美持妝粉底SPF10/PA++30ml/防曬/粉底液)",
        "產品系列": "Home\\品牌旗艦\\Estee Lauder 雅詩蘭黛\\彩妝系列\\底妝",
        "優惠期間": "09/13~09/18",
        "產品描述": "['24小時持久抗暗沉', '完美服貼，零細紋、零瑕疵', '不浮粉結塊零油光']",
        "所有價格": {
            "市售價": 3234,
            "促銷價": 2100,
            "折扣後價格": 1900
        },
        "資料更新時間": "2022-09-16 01:24:24"
    },
    {
        "品牌": "Estee Lauder 雅詩蘭黛",
        "產品編號": "10123030",
        "產品名": "【Estee Lauder 雅詩蘭黛】微分子肌底原生露/櫻花版 100ml任選(一抹即嫩 秒滲透 超爆水/化妝水/水精華)",
        "產品系列": "Home\\品牌旗艦\\Estee Lauder 雅詩蘭黛\\臉部保養\\化妝水",
        "優惠期間": "09/13~09/18",
        "產品描述": "['一抹即嫩！秒滲透 超爆水', '平滑粉刺，細嫩肌膚', '養出肌底透明光']",
        "所有價格": {
            "市售價": 3376,
            "促銷價": 2200,
            "折扣後價格": 2000
        },
        "資料更新時間": "2022-09-16 01:24:25"
    },
    {
        "品牌": "Estee Lauder 雅詩蘭黛",
        "產品編號": "8965385",
        "產品名": "【Estee Lauder 雅詩蘭黛】小棕瓶修護保濕組(特潤超導全方位修護露50ml(小棕瓶/精華液))",
        "產品系列": "Home\\彩妝保養\\專櫃保養品牌\\官方直營品牌\\EsteeLauder",
        "優惠期間": "09/13~09/18",
        "產品描述": "['一滴完美透亮', '肌膚彈潤更緊緻', '極速修護新革命']",
        "所有價格": {
            "市售價": 6053,
            "促銷價": 4200,
            "折扣後價格": 3800
        },
        "資料更新時間": "2022-09-16 01:24:25"
    },
    {
        "品牌": "Estee Lauder 雅詩蘭黛",
        "產品編號": "8820262",
        "產品名": "【Estee Lauder 雅詩蘭黛】粉持久完美持妝粉底30ml 線上百貨專櫃(NO.1底妝超長持久力/粉底液)",
        "產品系列": "Home\\彩妝保養\\專櫃彩妝品牌\\品項\\底妝",
        "優惠期間": "09/13~09/18",
        "產品描述": "['10CM 近看更完美，超長持久力']",
        "所有價格": {
            "促銷價": 2100,
            "折扣後價格": 1900
        },
        "資料更新時間": "2022-09-16 01:24:26"
    },
    {
        "品牌": "Estee Lauder 雅詩蘭黛",
        "產品編號": "10122899",
        "產品名": "【Estee Lauder 雅詩蘭黛】原生露爆水肌嫩組(微分子肌底原生露/櫻花版200ml任選/新上市/化妝水/水精華)",
        "產品系列": "Home\\彩妝保養\\臉部保養\\\n化妝水",
        "優惠期間": "09/13~09/18",
        "產品描述": "['一抹即嫩！秒滲透 超爆水', '平滑粉刺，細嫩肌膚', '養出肌底透明光']",
        "所有價格": {
            "市售價": 5903,
            "促銷價": 4050,
            "折扣後價格": 3650
        },
        "資料更新時間": "2022-09-16 01:24:27"
    },
    {
        "品牌": "Estee Lauder 雅詩蘭黛",
        "產品編號": "10299928",
        "產品名": "【Estee Lauder 雅詩蘭黛】年輕無敵膠原霜 75ml(乳霜)",
        "產品系列": "Home\\彩妝保養\\專櫃保養品牌\\官方直營品牌\\EsteeLauder",
        "優惠期間": "09/13~09/18",
        "產品描述": "['無敵Q彈X無敵保濕X無敵清爽', '3大自然精萃 膠原蛋白作用科技']",
        "所有價格": {
            "市售價": 6203,
            "促銷價": 4350,
            "折扣後價格": 3950
        },
        "資料更新時間": "2022-09-16 01:24:28"
    },
    {
        "品牌": "Estee Lauder 雅詩蘭黛",
        "產品編號": "10242393",
        "產品名": "【Estee Lauder 雅詩蘭黛】粉持久輕透控油粉餅 SPF10(防曬)",
        "產品系列": "Home\\彩妝保養\\專櫃彩妝品牌\\精選品牌\\Estee Lauder",
        "優惠期間": "09/13~09/18",
        "產品描述": "['超控油 零暗沉', '毛孔神隱 零瑕疵', '抗水抗汗 透氣超清爽']",
        "所有價格": {
            "促銷價": 2050,
            "折扣後價格": 1850
        },
        "資料更新時間": "2022-09-16 01:24:29"
    },
    {
        "品牌": "Estee Lauder 雅詩蘭黛",
        "產品編號": "8820273",
        "產品名": "【Estee Lauder 雅詩蘭黛】粉嫩慾望潤色護唇膏3.2g(蘊含45%植萃保養油)",
        "產品系列": "Home\\彩妝保養\\臉部保養\\\n護唇膏",
        "優惠期間": "09/13~09/18",
        "產品描述": "['辣木籽油成份，高效保濕不顯唇紋', '12小時顯色持久，帶有淡淡浪漫', '花瓣絲絨質地，打造最時髦的浪漫']",
        "所有價格": {
            "促銷價": 1250
        },
        "資料更新時間": "2022-09-16 01:24:30"
    },
    {
        "品牌": "Estee Lauder 雅詩蘭黛",
        "產品編號": "10373978",
        "產品名": "【Estee Lauder 雅詩蘭黛】特潤全能修護亮眼霜15ml(全方位擊退黑眼圈細紋)",
        "產品系列": "Home\\彩妝保養\\臉部保養\\\n眼霜",
        "優惠期間": "09/13~09/18",
        "產品描述": "['明亮黑眼圈 撫平眼周細紋', '修護眼周肌膚', '100小時長效保濕']",
        "所有價格": {
            "市售價": 3700,
            "促銷價": 2750,
            "折扣後價格": 2550
        },
        "資料更新時間": "2022-09-16 01:24:31"
    },
    {
        "品牌": "Estee Lauder 雅詩蘭黛",
        "產品編號": "8820190",
        "產品名": "【Estee Lauder 雅詩蘭黛】特潤超導全方位修護露30ml(No.1小棕瓶 彈嫩發光/精華液)",
        "產品系列": "Home\\彩妝保養\\專櫃保養品牌\\官方直營品牌\\EsteeLauder",
        "優惠期間": "09/13~09/18",
        "產品描述": "['一滴完美透亮\\u3000肌膚彈潤更緊緻']",
        "所有價格": {
            "促銷價": 2950,
            "折扣後價格": 2750
        },
        "資料更新時間": "2022-09-16 01:24:31"
    },
    {
        "品牌": "Estee Lauder 雅詩蘭黛",
        "產品編號": "10440790",
        "產品名": "【Estee Lauder 雅詩蘭黛】年輕金三角保養組(原生露 15ml +小棕瓶7ml+無敵膠原霜7ml)",
        "產品系列": "Home\\彩妝保養\\專櫃保養品牌\\官方直營品牌\\EsteeLauder",
        "產品描述": "['肌膚彈潤更緊緻', '平滑粉刺 秒滲透 超爆水', '無敵Q彈X無敵保濕X無敵清爽']",
        "所有價格": {
            "市售價": 1298,
            "促銷價": 999
        },
        "資料更新時間": "2022-09-16 01:24:32"
    },
    {
        "品牌": "Estee Lauder 雅詩蘭黛",
        "產品編號": "8820267",
        "產品名": "【Estee Lauder 雅詩蘭黛】粉保濕水啵啵妝前精華40ml(妝前保濕提亮)",
        "產品系列": "Home\\品牌旗艦\\Estee Lauder 雅詩蘭黛\\彩妝系列\\底妝",
        "優惠期間": "09/13~09/18",
        "產品描述": "['妝前保濕提亮，提升妝容服貼度']",
        "所有價格": {
            "促銷價": 2050,
            "折扣後價格": 1850
        },
        "資料更新時間": "2022-09-16 01:24:33"
    },
    {
        "品牌": "Estee Lauder 雅詩蘭黛",
        "產品編號": "8820193",
        "產品名": "【Estee Lauder 雅詩蘭黛】特潤超導賦活精萃20ml(小棕縮時精萃)",
        "產品系列": "Home\\彩妝保養\\專櫃保養品牌\\官方直營品牌\\EsteeLauder",
        "優惠期間": "09/13~09/18",
        "產品描述": "['1滴全能 1小時危「肌」歸零']",
        "所有價格": {
            "促銷價": 3350,
            "折扣後價格": 3150
        },
        "資料更新時間": "2022-09-16 01:24:34"
    },
    {
        "品牌": "Estee Lauder 雅詩蘭黛",
        "產品編號": "10265708",
        "產品名": "【Estee Lauder 雅詩蘭黛】爆水嫩亮修護雙星組(特潤超導全方位修護露50ml+微分子肌底原生露100ml/精華液)",
        "產品系列": "Home\\彩妝保養\\專櫃保養品牌\\官方直營品牌\\EsteeLauder",
        "優惠期間": "09/13~09/18",
        "產品描述": "['一滴完美透亮', '肌膚彈潤更緊緻', '極速修護新革命']",
        "所有價格": {
            "市售價": 9792,
            "促銷價": 6400,
            "折扣後價格": 5800
        },
        "資料更新時間": "2022-09-16 01:24:35"
    },
    {
        "品牌": "Estee Lauder 雅詩蘭黛",
        "產品編號": "9093366",
        "產品名": "【Estee Lauder 雅詩蘭黛】粉持久持妝潤色妝前乳30ml(全天粉嫩持妝SPF45/PA++++防曬)",
        "產品系列": "Home\\彩妝保養\\專櫃彩妝品牌\\品項\\隔離/飾底乳",
        "優惠期間": "09/13~09/18",
        "產品描述": "['無油配方 輕盈質地', '妝前一抹立即修飾黯沉、勻亮膚色', '有效抗氧化 溫和物理性防曬成份']",
        "所有價格": {
            "促銷價": 1750
        },
        "資料更新時間": "2022-09-16 01:24:36"
    },
    {
        "品牌": "Estee Lauder 雅詩蘭黛",
        "產品編號": "8820191",
        "產品名": "【Estee Lauder 雅詩蘭黛】特潤超導全方位修護露50ml(No.1小棕瓶 彈嫩發光/精華液)",
        "產品系列": "Home\\彩妝保養\\專櫃保養品牌\\官方直營品牌\\EsteeLauder",
        "優惠期間": "09/13~09/18",
        "產品描述": "['一滴完美透亮\\u3000肌膚彈潤更緊緻']",
        "所有價格": {
            "促銷價": 4200,
            "折扣後價格": 3800
        },
        "資料更新時間": "2022-09-16 01:24:37"
    },
    {
        "品牌": "Estee Lauder 雅詩蘭黛",
        "產品編號": "8820277",
        "產品名": "【Estee Lauder 雅詩蘭黛】絕對慾望奢華潤唇膏3.5g(絕對顯色滋潤)",
        "產品系列": "Home\\彩妝保養\\專櫃彩妝品牌\\精選品牌\\Estee Lauder",
        "優惠期間": "09/13~09/18",
        "產品描述": "['辣木籽油成份，高效保濕不顯唇紋', '12小時顯色持久，帶有淡淡浪漫', '花瓣絲絨質地，打造最時髦的浪漫']",
        "所有價格": {
            "促銷價": 1250
        },
        "資料更新時間": "2022-09-16 01:24:38"
    },
    {
        "品牌": "Estee Lauder 雅詩蘭黛",
        "產品編號": "9918290",
        "產品名": "【Estee Lauder 雅詩蘭黛】年輕無敵亮顏霜75ml",
        "產品系列": "Home\\彩妝保養\\專櫃保養品牌\\官方直營品牌\\EsteeLauder",
        "優惠期間": "09/13~09/18",
        "產品描述": "['突破性奇蹟辣木生命精萃X莓果C', '長效保濕，肌膚潤滑有感', '由內而外散發彈亮光']",
        "所有價格": {
            "促銷價": 4500,
            "折扣後價格": 4100
        },
        "資料更新時間": "2022-09-16 01:24:39"
    },
    {
        "品牌": "Estee Lauder 雅詩蘭黛",
        "產品編號": "8820263",
        "產品名": "【Estee Lauder 雅詩蘭黛】粉保濕訂製粉底精華SPF20/PA+++30ml(革命性保濕底妝/防曬/粉底液)",
        "產品系列": "Home\\品牌旗艦\\Estee Lauder 雅詩蘭黛\\彩妝系列\\底妝",
        "優惠期間": "09/13~09/18",
        "產品描述": "['素顏美，上妝更美!', '底妝保濕新極限 全天聚水閃耀', '植萃粉保濕 親膚粉服貼']",
        "所有價格": {
            "促銷價": 2250,
            "折扣後價格": 2050
        },
        "資料更新時間": "2022-09-16 01:24:39"
    },
    {
        "品牌": "Estee Lauder 雅詩蘭黛",
        "產品編號": "8820192",
        "產品名": "【Estee Lauder 雅詩蘭黛】Pro極速緊緻肌密全能精華 50ml(小銀瓶)",
        "產品系列": "Home\\彩妝保養\\臉部保養\\\n精華液",
        "優惠期間": "09/13~09/18",
        "產品描述": "['肌膚全面賦活，澎潤一觸可及', '打造健康肌膚，緊實效果', '提早使用更能鞏固肌膚年輕結構']",
        "所有價格": {
            "促銷價": 4750,
            "折扣後價格": 4350
        },
        "資料更新時間": "2022-09-16 01:24:40"
    },
    {
        "品牌": "Estee Lauder 雅詩蘭黛",
        "產品編號": "10112251",
        "產品名": "【Estee Lauder 雅詩蘭黛】粉持久絲柔空氣蜜粉9g",
        "產品系列": "Home\\彩妝保養\\專櫃彩妝品牌\\精選品牌\\Estee Lauder",
        "優惠期間": "09/13~09/18",
        "產品描述": "['一抹自帶濾鏡', '化身空氣柔焦肌', '氣墊篩網 輕鬆掌握取粉份量']",
        "所有價格": {
            "促銷價": 1900
        },
        "資料更新時間": "2022-09-16 01:24:41"
    },
    {
        "品牌": "Estee Lauder 雅詩蘭黛",
        "產品編號": "10095164",
        "產品名": "【Estee Lauder 雅詩蘭黛】年輕無敵膠原晚霜50ml",
        "產品系列": "Home\\彩妝保養\\專櫃保養品牌\\官方直營品牌\\EsteeLauder",
        "優惠期間": "09/13~09/18",
        "產品描述": "[]",
        "所有價格": {
            "促銷價": 3900,
            "折扣後價格": 3700
        },
        "資料更新時間": "2022-09-16 01:24:42"
    },
    {
        "品牌": "Estee Lauder 雅詩蘭黛",
        "產品編號": "8892554",
        "產品名": "【Estee Lauder 雅詩蘭黛】歡沁香水-50ml(清新花香)",
        "產品系列": "Home\\彩妝保養\\香水\\香調\\花香調",
        "優惠期間": "09/13~09/18",
        "產品描述": "[]",
        "所有價格": {
            "促銷價": 2600,
            "折扣後價格": 2400
        },
        "資料更新時間": "2022-09-16 01:24:43"
    },
    {
        "品牌": "Estee Lauder 雅詩蘭黛",
        "產品編號": "8820710",
        "產品名": "【Estee Lauder 雅詩蘭黛】粉持久完美持妝粉底替換壓頭(壓頭單售不含粉底)",
        "產品系列": "Home\\彩妝保養\\開架彩妝品牌\\美容工具\\化妝周邊",
        "優惠期間": "09/13~09/18",
        "產品描述": "['10CM 近看更完美，超長持久']",
        "所有價格": {
            "促銷價": 150
        },
        "資料更新時間": "2022-09-16 01:24:44"
    },
    {
        "品牌": "Estee Lauder 雅詩蘭黛",
        "產品編號": "8820204",
        "產品名": "【Estee Lauder 雅詩蘭黛】Pro極速淨膚精華50ml(改善暗沉展現淨透光)",
        "產品系列": "Home\\彩妝保養\\臉部保養\\\n精華液",
        "優惠期間": "09/13~09/18",
        "產品描述": "['去斑淨白×勻亮膚色', '極速淨透光科技', '一滴移除蠟黃暗沉']",
        "所有價格": {
            "促銷價": 4700,
            "折扣後價格": 4300
        },
        "資料更新時間": "2022-09-16 01:24:45"
    },
    {
        "品牌": "Estee Lauder 雅詩蘭黛",
        "產品編號": "8820264",
        "產品名": "【Estee Lauder 雅詩蘭黛】白金級寶石光精華粉底 SPF20/ PA+++30ml(頂級底妝/防曬)",
        "產品系列": "Home\\彩妝保養\\專櫃彩妝品牌\\精選品牌\\Estee Lauder",
        "優惠期間": "09/13~09/18",
        "產品描述": "['頂級奢華保養成份']",
        "所有價格": {
            "促銷價": 4250,
            "折扣後價格": 3850
        },
        "資料更新時間": "2022-09-16 01:24:45"
    },
    {
        "品牌": "Estee Lauder 雅詩蘭黛",
        "產品編號": "10095163",
        "產品名": "【Estee Lauder 雅詩蘭黛】Pro 全能防曬超輕感水凝露 30ml(SPF 30/PA+++防曬)",
        "產品系列": "Home\\彩妝保養\\底妝\\底妝\\隔離霜",
        "優惠期間": "09/13~09/18",
        "產品描述": "[]",
        "所有價格": {
            "促銷價": 2300,
            "折扣後價格": 2100
        },
        "資料更新時間": "2022-09-16 01:24:46"
    },
    {
        "品牌": "Estee Lauder 雅詩蘭黛",
        "產品編號": "8892553",
        "產品名": "【Estee Lauder 雅詩蘭黛】歡沁香水-30ml(清新花香)",
        "產品系列": "Home\\彩妝保養\\香水\\香調\\花香調",
        "優惠期間": "09/13~09/18",
        "產品描述": "[]",
        "所有價格": {
            "促銷價": 1800
        },
        "資料更新時間": "2022-09-16 01:24:47"
    },
    {
        "品牌": "Estee Lauder 雅詩蘭黛",
        "產品編號": "10112562",
        "產品名": "【Estee Lauder 雅詩蘭黛】絕對慾望訂製眼彩盤6g",
        "產品系列": "Home\\彩妝保養\\專櫃彩妝品牌\\精選品牌\\Estee Lauder",
        "優惠期間": "09/13~09/18",
        "產品描述": "['色澤飽滿 持久顯色', '粉質細緻 輕鬆暈染', '百變眼妝 輕鬆創造']",
        "所有價格": {
            "促銷價": 2100,
            "折扣後價格": 1900
        },
        "資料更新時間": "2022-09-16 01:24:48"
    },
    {
        "品牌": "Estee Lauder 雅詩蘭黛",
        "產品編號": "8820258",
        "產品名": "【Estee Lauder 雅詩蘭黛】白金級極萃賦活花秘凝露200ml(明亮柔嫩滋養肌膚)",
        "產品系列": "Home\\彩妝保養\\臉部保養\\\n化妝水",
        "優惠期間": "09/13~09/18",
        "產品描述": "['一滴激升肌膚八大能量']",
        "所有價格": {
            "促銷價": 5250,
            "折扣後價格": 4850
        },
        "資料更新時間": "2022-09-16 01:24:49"
    },
    {
        "品牌": "Estee Lauder 雅詩蘭黛",
        "產品編號": "10289044",
        "產品名": "【Estee Lauder 雅詩蘭黛】Modern Muse繆思香水 50ml",
        "產品系列": "Home\\彩妝保養\\香水\\熱銷香(A-Z)\\EsteeLauder雅詩蘭黛",
        "優惠期間": "09/13~09/18",
        "產品描述": "['注入兩種茉莉萃取精華', '豐富的花香與木質香', '襯托出女性精采生活中的每一面']",
        "所有價格": {
            "促銷價": 4050,
            "折扣後價格": 3650
        },
        "資料更新時間": "2022-09-16 01:24:50"
    },
    {
        "品牌": "Estee Lauder 雅詩蘭黛",
        "產品編號": "8820259",
        "產品名": "【Estee Lauder 雅詩蘭黛】白金級極萃賦活花秘乳霜50ml(打造彈嫩巔峰)",
        "產品系列": "Home\\品牌旗艦\\Estee Lauder 雅詩蘭黛\\臉部保養\\乳液乳霜",
        "優惠期間": "09/13~09/18",
        "產品描述": "['打造彈嫩巔峰 肌膚完美細緻']",
        "所有價格": {
            "促銷價": 12600,
            "折扣後價格": 11400
        },
        "資料更新時間": "2022-09-16 01:24:51"
    },
    {
        "品牌": "Estee Lauder 雅詩蘭黛",
        "產品編號": "9265772",
        "產品名": "【Estee Lauder 雅詩蘭黛】粉持久輕霧光水粉底SPF20 30ml(持妝控油 輕盈保濕/防曬/粉底液)",
        "產品系列": "Home\\品牌旗艦\\Estee Lauder 雅詩蘭黛\\彩妝系列\\底妝",
        "優惠期間": "09/13~09/18",
        "產品描述": "[]",
        "所有價格": {
            "促銷價": 2100,
            "折扣後價格": 1900
        },
        "資料更新時間": "2022-09-16 01:24:52"
    },
    {
        "品牌": "Estee Lauder 雅詩蘭黛",
        "產品編號": "8820279",
        "產品名": "【Estee Lauder 雅詩蘭黛】特潤奶霜唇膏1.8g(小金管)",
        "產品系列": "Home\\品牌旗艦\\Estee Lauder 雅詩蘭黛\\彩妝系列\\唇膏",
        "優惠期間": "09/13~09/18",
        "產品描述": "['辣木籽油成份，高效保濕不顯唇紋', '12小時顯色持久，帶有淡淡浪漫', '花瓣絲絨質地，打造最時髦的浪漫']",
        "所有價格": {
            "促銷價": 1270
        },
        "資料更新時間": "2022-09-16 01:24:53"
    },
    {
        "品牌": "Estee Lauder 雅詩蘭黛",
        "產品編號": "8820265",
        "產品名": "【Estee Lauder 雅詩蘭黛】毛孔神隱柔焦膏30ml(隱形毛孔、撫平細紋)",
        "產品系列": "Home\\彩妝保養\\專櫃彩妝品牌\\精選品牌\\Estee Lauder",
        "優惠期間": "09/13~09/18",
        "產品描述": "['隱形毛孔、撫平細紋']",
        "所有價格": {
            "促銷價": 1750
        },
        "資料更新時間": "2022-09-16 01:24:54"
    },
    {
        "品牌": "Estee Lauder 雅詩蘭黛",
        "產品編號": "9918776",
        "產品名": "【Estee Lauder 雅詩蘭黛】頂級黑鑽入門組(黑鑽微導金萃30ml+花秘乳霜7ml+黑鑽亮眼精萃5ml+花秘凝露15ml)",
        "產品系列": "Home\\彩妝保養\\專櫃保養品牌\\官方直營品牌\\EsteeLauder",
        "優惠期間": "09/13~09/18",
        "產品描述": "['一抹淨透緊亮，成就鑽光美肌', '激活青春 x 緊緻拉提', '注入珍貴松露精華']",
        "所有價格": {
            "市售價": 12775,
            "促銷價": 8350,
            "折扣後價格": 7550
        },
        "資料更新時間": "2022-09-16 01:24:55"
    },
    {
        "品牌": "Estee Lauder 雅詩蘭黛",
        "產品編號": "9776072",
        "產品名": "【Estee Lauder 雅詩蘭黛】粉嫩慾望晶透潤唇膏(高效澎彈保濕)",
        "產品系列": "Home\\品牌旗艦\\Estee Lauder 雅詩蘭黛\\彩妝系列\\護唇",
        "優惠期間": "09/13~09/18",
        "產品描述": "[]",
        "所有價格": {
            "促銷價": 1300
        },
        "資料更新時間": "2022-09-16 01:24:56"
    },
    {
        "品牌": "Estee Lauder 雅詩蘭黛",
        "產品編號": "8820278",
        "產品名": "【Estee Lauder 雅詩蘭黛】絕對慾望柔霧唇膏3.5g(粉霧柔嫩絲滑)",
        "產品系列": "Home\\彩妝保養\\專櫃彩妝品牌\\精選品牌\\Estee Lauder",
        "優惠期間": "09/13~09/18",
        "產品描述": "['辣木籽油成份，高效保濕不顯唇紋', '12小時顯色持久，帶有淡淡浪漫', '花瓣絲絨質地，打造最時髦的浪漫']",
        "所有價格": {
            "促銷價": 1250
        },
        "資料更新時間": "2022-09-16 01:24:57"
    },
    {
        "品牌": "Estee Lauder 雅詩蘭黛",
        "產品編號": "10312404",
        "產品名": "【Estee Lauder 雅詩蘭黛】微分子晶透面膜6片裝",
        "產品系列": "Home\\彩妝保養\\臉部保養\\\n面膜",
        "優惠期間": "09/13~09/18",
        "產品描述": "['10分鐘立即感受!', '超濃縮微分子精華', '肌膚深度滋潤 水嫩清新淨透']",
        "所有價格": {
            "促銷價": 2650,
            "折扣後價格": 2450
        },
        "資料更新時間": "2022-09-16 01:24:58"
    },
    {
        "品牌": "Estee Lauder 雅詩蘭黛",
        "產品編號": "8820274",
        "產品名": "【Estee Lauder 雅詩蘭黛】粉嫩慾望蜜糖嫩唇霜12g(提亮潤澤)",
        "產品系列": "Home\\品牌旗艦\\Estee Lauder 雅詩蘭黛\\彩妝系列\\護唇",
        "優惠期間": "09/13~09/18",
        "產品描述": "['蜜糖微晶體，擺脫唇部乾燥老皮']",
        "所有價格": {
            "促銷價": 1300
        },
        "資料更新時間": "2022-09-16 01:24:58"
    },
    {
        "品牌": "Estee Lauder 雅詩蘭黛",
        "產品編號": "9776077",
        "產品名": "【Estee Lauder 雅詩蘭黛】白金級黑鑽松露雙效奇蹟霜50ml(肌膚澎彈緊潤)",
        "產品系列": "Home\\彩妝保養\\臉部保養\\\n乳霜",
        "優惠期間": "09/13~09/18",
        "產品描述": "[]",
        "所有價格": {
            "促銷價": 20650,
            "折扣後價格": 18650
        },
        "資料更新時間": "2022-09-16 01:24:59"
    },
    {
        "品牌": "Estee Lauder 雅詩蘭黛",
        "產品編號": "9776075",
        "產品名": "【Estee Lauder 雅詩蘭黛】黑鑽松露賦活微導金萃30ml(緊塑肌膚x澎彈光亮)",
        "產品系列": "Home\\彩妝保養\\專櫃保養品牌\\官方直營品牌\\EsteeLauder",
        "優惠期間": "09/13~09/18",
        "產品描述": "[]",
        "所有價格": {
            "促銷價": 8350,
            "折扣後價格": 7550
        },
        "資料更新時間": "2022-09-16 01:25:00"
    },
    {
        "品牌": "Estee Lauder 雅詩蘭黛",
        "產品編號": "8820260",
        "產品名": "【Estee Lauder 雅詩蘭黛】白金級極萃賦活花秘精萃30ml(不凋花賦活科技)",
        "產品系列": "Home\\彩妝保養\\專櫃保養品牌\\官方直營品牌\\EsteeLauder",
        "優惠期間": "09/13~09/18",
        "產品描述": "['珍稀「凍齡因子」，結合花秘結晶', '激升膠原蛋白生長 打造肌膚巔峰']",
        "所有價格": {
            "促銷價": 12800,
            "折扣後價格": 11600
        },
        "資料更新時間": "2022-09-16 01:25:01"
    },
    {
        "品牌": "Estee Lauder 雅詩蘭黛",
        "產品編號": "10289048",
        "產品名": "【Estee Lauder 雅詩蘭黛】歡沁香體乳液 250ml",
        "產品系列": "Home\\彩妝保養\\香水\\香水周邊\\身體乳",
        "產品描述": "['清新活潑 溫暖沉靜 粉嫩花香', '使用獨有自然花種「粉紅莓」', '柔軟萃取花朵本身香味']",
        "所有價格": {
            "促銷價": 2050
        },
        "資料更新時間": "2022-09-16 01:25:02"
    },
    {
        "品牌": "Estee Lauder 雅詩蘭黛",
        "產品編號": "9918553",
        "產品名": "【Estee Lauder 雅詩蘭黛】白金花秘爆水凝露組(花秘凝露200ml+黑鑽松露微導金萃5ml+花秘凝露15ml)",
        "產品系列": "Home\\彩妝保養\\臉部保養\\\n化妝水",
        "優惠期間": "09/13~09/18",
        "產品描述": "['強勢補足水潤度', '萃取喜馬拉雅極地冰晶花珍稀', '有效激活肌膚明亮、保濕']",
        "所有價格": {
            "市售價": 7035,
            "促銷價": 5250,
            "折扣後價格": 4850
        },
        "資料更新時間": "2022-09-16 01:25:03"
    },
    {
        "品牌": "Estee Lauder 雅詩蘭黛",
        "產品編號": "10289046",
        "產品名": "【Estee Lauder 雅詩蘭黛】美麗香水75ml",
        "產品系列": "Home\\彩妝保養\\香水\\熱銷香(A-Z)\\EsteeLauder雅詩蘭黛",
        "優惠期間": "09/13~09/18",
        "產品描述": "['雅詩蘭黛夫人耗時四年創造', '集千朵鮮花馥郁之精華', '源自最動人的回憶及浪漫情愫']",
        "所有價格": {
            "促銷價": 3300,
            "折扣後價格": 3100
        },
        "資料更新時間": "2022-09-16 01:25:03"
    },
    {
        "品牌": "Estee Lauder 雅詩蘭黛",
        "產品編號": "9324040",
        "產品名": "【Estee Lauder 雅詩蘭黛】柔霧絲絨唇釉9ml(獨特花瓣絲絨質地)",
        "產品系列": "Home\\品牌旗艦\\Estee Lauder 雅詩蘭黛\\彩妝系列\\唇膏",
        "優惠期間": "09/13~09/18",
        "產品描述": "['辣木籽油成份，高效保濕不顯唇紋', '12小時顯色持久，帶有淡淡浪漫', '花瓣絲絨質地，打造最時髦的浪漫']",
        "所有價格": {
            "促銷價": 1270
        },
        "資料更新時間": "2022-09-16 01:25:04"
    },
    {
        "品牌": "Estee Lauder 雅詩蘭黛",
        "產品編號": "9776076",
        "產品名": "【Estee Lauder 雅詩蘭黛】白金級黑鑽松露奇蹟修護亮眼精萃15ml(全新逆齡青春科技x修護眼周肌膚)",
        "產品系列": "Home\\品牌旗艦\\Estee Lauder 雅詩蘭黛\\臉部保養\\眼部護理",
        "優惠期間": "09/13~09/18",
        "產品描述": "[]",
        "所有價格": {
            "促銷價": 6800,
            "折扣後價格": 6200
        },
        "資料更新時間": "2022-09-16 01:25:05"
    },
    {
        "品牌": "Estee Lauder 雅詩蘭黛",
        "產品編號": "8820256",
        "產品名": "【Estee Lauder 雅詩蘭黛】Pro極速發光安瓶10ml*4(極速發光全效美白)",
        "產品系列": "Home\\彩妝保養\\臉部保養\\\n精華液",
        "優惠期間": "09/13~09/18",
        "產品描述": "['抑制暗沉均勻膚色', '讓肌膚達到前所未有亮度巔峰', '28天極速發光療程，透亮每一刻']",
        "所有價格": {
            "促銷價": 4350,
            "折扣後價格": 3950
        },
        "資料更新時間": "2022-09-16 01:25:06"
    },
    {
        "品牌": "Estee Lauder 雅詩蘭黛",
        "產品編號": "10112252",
        "產品名": "【Estee Lauder 雅詩蘭黛】絕對慾望持色柔霧腮紅7g",
        "產品系列": "Home\\彩妝保養\\底妝\\\n腮紅",
        "優惠期間": "09/13~09/18",
        "產品描述": "['柔霧質地 氣色立顯', '細緻粉體好暈染', '附彩妝刷，便於補妝']",
        "所有價格": {
            "促銷價": 1650
        },
        "資料更新時間": "2022-09-16 01:25:07"
    },
    {
        "品牌": "Estee Lauder 雅詩蘭黛",
        "產品編號": "8820261",
        "產品名": "【Estee Lauder 雅詩蘭黛】白金級極萃賦活花秘眼霜15ml(冰肌乳霜質地  一抹化水)",
        "產品系列": "Home\\彩妝保養\\臉部保養\\\n眼霜",
        "優惠期間": "09/13~09/18",
        "產品描述": "['全面賦活眼周肌膚', '彈嫩水亮再升級', '「凍齡因子」協同膠原蛋白作用，']",
        "所有價格": {
            "促銷價": 6300,
            "折扣後價格": 5700
        },
        "資料更新時間": "2022-09-16 01:25:08"
    },
    {
        "品牌": "ADVANCED 艾德凡斯",
        "產品編號": "7928577",
        "產品名": "【ADVANCED 艾德凡斯】杜鵑花酸亮白精華乳霜 30ml(贈雅詩蘭黛 超能紅石榴微循環精華30ml)",
        "產品系列": "Home\\彩妝保養\\開架保養品牌\\★精選品牌★\\ADVANCED艾德凡斯",
        "產品描述": "['吳茵如美容協會理事長熱情推薦', '美國Amazon亞馬遜熱銷', '全台首創免費遠距美容諮詢服務']",
        "所有價格": {
            "市售價": 1299,
            "促銷價": 699
        },
        "資料更新時間": "2022-09-16 01:25:09"
    },
    {
        "品牌": "ADVANCED 艾德凡斯",
        "產品編號": "7928579",
        "產品名": "【ADVANCED 艾德凡斯】緊緻修護角鯊烷精華液 30ml(贈雅詩蘭黛 超能紅石榴微循環精華30ml)",
        "產品系列": "Home\\彩妝保養\\開架保養品牌\\★精選品牌★\\ADVANCED艾德凡斯",
        "產品描述": "['吳茵如美容協會理事長熱情推薦', '美國Amazon亞馬遜熱銷', '全台首創免費遠距美容諮詢服務']",
        "所有價格": {
            "市售價": 1499,
            "促銷價": 699
        },
        "資料更新時間": "2022-09-16 01:25:10"
    },
    {
        "品牌": "ADVANCED 艾德凡斯",
        "產品編號": "7928576",
        "產品名": "【ADVANCED 艾德凡斯】ADVANCED B5保濕超純補水玻尿酸精華液30ml(贈雅詩蘭黛 超能紅石榴微循環精華30ml)",
        "產品系列": "Home\\彩妝保養\\開架保養品牌\\★精選品牌★\\ADVANCED艾德凡斯",
        "產品描述": "['吳茵如美容協會理事長熱情推薦', '美國Amazon亞馬遜熱銷', '全台首創免費遠距美容諮詢服務']",
        "所有價格": {
            "市售價": 2037,
            "促銷價": 699
        },
        "資料更新時間": "2022-09-16 01:25:11"
    },
    {
        "品牌": "ADVANCED 艾德凡斯",
        "產品編號": "7931550",
        "產品名": "【ADVANCED 艾德凡斯】淨白維生素B3菸鹼胺控油精華液 30ml(贈雅詩蘭黛 超能紅石榴微循環精華30ml)",
        "產品系列": "Home\\彩妝保養\\開架保養品牌\\★精選品牌★\\ADVANCED艾德凡斯",
        "產品描述": "['吳茵如美容協會理事長熱情推薦', '美國Amazon亞馬遜熱銷', '全台首創免費遠距美容諮詢服務']",
        "所有價格": {
            "市售價": 1499,
            "促銷價": 699
        },
        "資料更新時間": "2022-09-16 01:25:12"
    },
    {
        "品牌": "西歐科技",
        "產品編號": "10343695",
        "產品名": "【西歐科技】USB充電式LED三檔調光美妝鏡 CME-MF100(贈雅詩蘭黛 超能紅石榴微循環精華30ml)",
        "產品系列": "Home\\家電\\美容電器\\美容小物\\化妝燈鏡",
        "優惠期間": "09/01~09/30",
        "產品描述": "['美肌效果', '智慧觸控亮屏', '180度翻轉可拆卸支架']",
        "所有價格": {
            "促銷價": 599,
            "折扣後價格": 527
        },
        "資料更新時間": "2022-09-16 01:25:13"
    }
]